saferx/__init__.py
saferx/data_processing_m1/__init__.py
saferx/data_processing_m1/crf_data.py
saferx/data_processing_m1/location_data.py
saferx/data_processing_m1/sensor_data.py
saferx/data_processing_m2/__init__.py
saferx/data_processing_m2/crf_data.py
saferx/data_processing_m2/location_data.py
saferx/data_processing_m2/sensor_data.py
saferx/model1/__init__.py
saferx/model1/dataloader.py
saferx/model1/model.py
saferx/model1/predictor.py
saferx/model1/model/tft_model.pkl
saferx/model1/model/tft_model_converted.pth
saferx/model2/__init__.py
saferx/model2/dataloader.py
saferx/model2/model.py
saferx/model2/predictor.py
saferx/model2/model/final_model.pkl
saferx/model2/model/final_model_converted.pth
saferx/model2/model/final_model_revised.pkl
saferx/model2/model/model.pth
saferx-0.7.0.dist-info/METADATA
saferx-0.7.0.dist-info/WHEEL
saferx-0.7.0.dist-info/top_level.txt
saferx-0.7.0.dist-info/RECORD
