Metadata-Version: 2.1
Name: saferx
Version: 0.7.0
Summary: SAFER package
Home-page: https://github.com/gachon-CCLab/SAFER_LIB.git
Author: rirakang
Author-email: rirakang@gachon.ac.kr
License: UNKNOWN
Platform: UNKNOWN
Requires-Python: >=3.9
Requires-Dist: torch
Requires-Dist: pandas
Requires-Dist: numpy
Requires-Dist: scikit-learn
